pydub-stubs/__init__.pyi
pydub-stubs/audio_segment.pyi
pydub-stubs/effects.pyi
pydub-stubs/exceptions.pyi
pydub-stubs/generators.pyi
pydub-stubs/playback.pyi
pydub-stubs/scipy_effects.pyi
pydub-stubs/silence.pyi
pydub-stubs/utils.pyi
pydub_stubs-0.25.1.6.dist-info/LICENSE
pydub_stubs-0.25.1.6.dist-info/METADATA
pydub_stubs-0.25.1.6.dist-info/WHEEL
pydub_stubs-0.25.1.6.dist-info/RECORD
