Metadata-Version: 2.1
Name: pydub-stubs
Version: 0.25.1.6
Summary: Stub-only package containing type information for pydub
Home-page: https://github.com/clo4/pydub-stubs
License: ISC
Keywords: pydub,types,typing,stubs
Author: SeparateRecords
Author-email: hey@clo4.net
Requires-Python: >=3.9,<4.0
Classifier: Development Status :: 5 - Production/Stable
Classifier: Intended Audience :: Developers
Classifier: License :: OSI Approved
Classifier: License :: OSI Approved :: ISC License (ISCL)
Classifier: Programming Language :: Python :: 3
Classifier: Programming Language :: Python :: 3.9
Classifier: Programming Language :: Python :: 3.10
Classifier: Programming Language :: Python :: 3.11
Classifier: Programming Language :: Python :: 3.12
Classifier: Programming Language :: Python :: 3.13
Classifier: Typing :: Stubs Only
Requires-Dist: typing-extensions (>=4.0.0)
Project-URL: Repository, https://github.com/clo4/pydub-stubs
